[
    {
        "allowed_clans": [
            "unicorn"
        ],
        "clan": "unicorn",
        "cost": "2",
        "deck_limit": 3,
        "element": [],
        "fate": null,
        "glory": 2,
        "honor": null,
        "id": "worldly-shiotome",
        "influence_cost": null,
        "influence_pool": null,
        "is_banned": false,
        "is_banned_in_jade": false,
        "is_banned_in_skirmish": false,
        "is_restricted": false,
        "is_restricted_in_jade": false,
        "military": "2",
        "military_bonus": null,
        "name": "Worldly Shiotome",
        "name_extra": null,
        "political": "2",
        "political_bonus": null,
        "role_restriction": null,
        "side": "dynasty",
        "strength": null,
        "strength_bonus": null,
        "text": "<b>Reaction:</b> After you play a <em>Gaijin</em> card - honor this character.\n<b>Card design by <em>Legend of the Five Rings</em> community.</b>",
        "traits": [
            "bushi",
            "cavalry",
            "battle-maiden"
        ],
        "type": "character",
        "unicity": false
    }
]